chaoshumio/__init__.py
chaoshumio/control.py
chaoshumio/notification.py
chaoshumio/probes.py
chaoshumio/tolerances.py
chaostoolkit_humio-0.6.0.dist-info/WHEEL
chaostoolkit_humio-0.6.0.dist-info/METADATA
chaostoolkit_humio-0.6.0.dist-info/licenses/LICENSE
chaostoolkit_humio-0.6.0.dist-info/RECORD
