Metadata-Version: 2.1
Name: chaostoolkit-humio
Version: 0.6.0
Summary: Reliably CLI
License: Apache-2.0
Author-email: Chaos Toolkit <contact@chaostoolkit.org>
Requires-Python: >=3.7
Classifier: Development Status :: 4 - Beta
Classifier: Intended Audience :: Developers
Classifier: License :: Freely Distributable
Classifier: License :: OSI Approved :: Apache Software License
Classifier: Operating System :: OS Independent
Classifier: Programming Language :: Python
Classifier: Programming Language :: Python :: 3
Classifier: Programming Language :: Python :: 3.10
Classifier: Programming Language :: Python :: 3.7
Classifier: Programming Language :: Python :: 3.8
Classifier: Programming Language :: Python :: 3.9
Classifier: Programming Language :: Python :: Implementation
Classifier: Programming Language :: Python :: Implementation :: CPython
Requires-Dist: chaostoolkit-lib>=1.33.1
Requires-Dist: requests
Provides-Extra: dev
Requires-Dist: black>=22.10.0; extra == "dev"
Requires-Dist: isort>=5.10.1; extra == "dev"
Requires-Dist: pytest>=7.2.0; extra == "dev"
Requires-Dist: coverage>=6.5.0; extra == "dev"
Requires-Dist: pytest-cov>=4.0.0; extra == "dev"
Requires-Dist: pytest-sugar>=0.9.5; extra == "dev"
Requires-Dist: types-requests; extra == "dev"
Requires-Dist: requests_mock; extra == "dev"
Requires-Dist: ruff; extra == "dev"
Requires-Dist: mypy; extra == "dev"
